LICENSE
MANIFEST.in
README.rst
setup.cfg
setup.py
django_fortunecookie.egg-info/PKG-INFO
django_fortunecookie.egg-info/SOURCES.txt
django_fortunecookie.egg-info/dependency_links.txt
django_fortunecookie.egg-info/not-zip-safe
django_fortunecookie.egg-info/requires.txt
django_fortunecookie.egg-info/top_level.txt
fortunecookie/__init__.py
fortunecookie/admin.py
fortunecookie/apps.py
fortunecookie/managers.py
fortunecookie/models.py
fortunecookie/fixtures/fortunecookies.json
fortunecookie/migrations/0001_initial.py
fortunecookie/migrations/__init__.py